ailabdc/__init__.py
ailabdc/client/__init__.py
ailabdc/client/func.py
ailabdc/client/models.py
ailabdc/client/remote.py
ailabdc/client/zaco.py
ailabdc_client-0.1.1.dist-info/METADATA
ailabdc_client-0.1.1.dist-info/WHEEL
ailabdc_client-0.1.1.dist-info/top_level.txt
ailabdc_client-0.1.1.dist-info/RECORD
